censys_client/__init__.py
censys_client/__main__.py
censys_client/client.py
censys_client-0.1.2.dist-info/LICENSE
censys_client-0.1.2.dist-info/METADATA
censys_client-0.1.2.dist-info/WHEEL
censys_client-0.1.2.dist-info/entry_points.txt
censys_client-0.1.2.dist-info/top_level.txt
censys_client-0.1.2.dist-info/RECORD
