Metadata-Version: 2.1
Name: censys-client
Version: 0.1.2
Summary: A censys client that allow to you to use multiple api key
Home-page: https://github.com/Inplex-sys/censys-client
Author: Inplex-sys
Author-email: Inplex-sys <Inplex-sys@protonmail.com>
Project-URL: Homepage, https://github.com/Inplex-sys/censys-client
Project-URL: Bug Tracker, https://github.com/Inplex-sys/censys-client/issues
Classifier: Programming Language :: Python :: 3
Classifier: License :: OSI Approved :: MIT License
Classifier: Operating System :: OS Independent
Requires-Python: >=3.0
License-File: LICENSE
Requires-Dist: requests
Requires-Dist: colored
